darbia/sns/__init__.py
darbia/sns/models.py
darbia/sns/sns_services.py
darbiadev_sands-0.1.0.dist-info/LICENSE
darbiadev_sands-0.1.0.dist-info/METADATA
darbiadev_sands-0.1.0.dist-info/WHEEL
darbiadev_sands-0.1.0.dist-info/top_level.txt
darbiadev_sands-0.1.0.dist-info/RECORD
