Metadata-Version: 2.1
Name: darbiadev-sands
Version: 0.1.0
Summary: A wrapper for S&S' API.
Author-email: Bradley Reynolds <bradley.reynolds@darbia.dev>
License: MIT
Project-URL: repository, https://github.com/darbiadev/darbiadev-sands/
Project-URL: documentation, https://docs.darbia.dev/darbiadev-sands/
Requires-Python: >=3.11
License-File: LICENSE
Requires-Dist: anyio ==4.0.0
Requires-Dist: certifi ==2023.7.22
Requires-Dist: h11 ==0.14.0
Requires-Dist: httpcore ==0.18.0
Requires-Dist: httpx ==0.25.0
Requires-Dist: idna ==3.4
Requires-Dist: sniffio ==1.3.0
Provides-Extra: dev
Requires-Dist: black ==23.9.1 ; extra == 'dev'
Requires-Dist: build ==1.0.3 ; extra == 'dev'
Requires-Dist: cfgv ==3.4.0 ; extra == 'dev'
Requires-Dist: click ==8.1.7 ; extra == 'dev'
Requires-Dist: distlib ==0.3.7 ; extra == 'dev'
Requires-Dist: filelock ==3.12.4 ; extra == 'dev'
Requires-Dist: identify ==2.5.30 ; extra == 'dev'
Requires-Dist: mypy-extensions ==1.0.0 ; extra == 'dev'
Requires-Dist: nodeenv ==1.8.0 ; extra == 'dev'
Requires-Dist: packaging ==23.2 ; extra == 'dev'
Requires-Dist: pathspec ==0.11.2 ; extra == 'dev'
Requires-Dist: pip-tools ==7.3.0 ; extra == 'dev'
Requires-Dist: platformdirs ==3.11.0 ; extra == 'dev'
Requires-Dist: pre-commit ==3.4.0 ; extra == 'dev'
Requires-Dist: pyproject-hooks ==1.0.0 ; extra == 'dev'
Requires-Dist: pyyaml ==6.0.1 ; extra == 'dev'
Requires-Dist: ruff ==0.0.292 ; extra == 'dev'
Requires-Dist: virtualenv ==20.24.5 ; extra == 'dev'
Requires-Dist: wheel ==0.41.2 ; extra == 'dev'
Provides-Extra: docs
Requires-Dist: alabaster ==0.7.13 ; extra == 'docs'
Requires-Dist: anyascii ==0.3.2 ; extra == 'docs'
Requires-Dist: astroid ==3.0.0 ; extra == 'docs'
Requires-Dist: babel ==2.13.0 ; extra == 'docs'
Requires-Dist: beautifulsoup4 ==4.12.2 ; extra == 'docs'
Requires-Dist: certifi ==2023.7.22 ; extra == 'docs'
Requires-Dist: charset-normalizer ==3.3.0 ; extra == 'docs'
Requires-Dist: docutils ==0.20.1 ; extra == 'docs'
Requires-Dist: furo ==2023.9.10 ; extra == 'docs'
Requires-Dist: idna ==3.4 ; extra == 'docs'
Requires-Dist: imagesize ==1.4.1 ; extra == 'docs'
Requires-Dist: jinja2 ==3.1.2 ; extra == 'docs'
Requires-Dist: markupsafe ==2.1.3 ; extra == 'docs'
Requires-Dist: packaging ==23.2 ; extra == 'docs'
Requires-Dist: pygments ==2.16.1 ; extra == 'docs'
Requires-Dist: pyyaml ==6.0.1 ; extra == 'docs'
Requires-Dist: releases ==2.1.1 ; extra == 'docs'
Requires-Dist: requests ==2.31.0 ; extra == 'docs'
Requires-Dist: semantic-version ==2.6.0 ; extra == 'docs'
Requires-Dist: snowballstemmer ==2.2.0 ; extra == 'docs'
Requires-Dist: soupsieve ==2.5 ; extra == 'docs'
Requires-Dist: sphinx ==7.2.6 ; extra == 'docs'
Requires-Dist: sphinx-autoapi ==3.0.0 ; extra == 'docs'
Requires-Dist: sphinx-basic-ng ==1.0.0b2 ; extra == 'docs'
Requires-Dist: sphinxcontrib-applehelp ==1.0.7 ; extra == 'docs'
Requires-Dist: sphinxcontrib-devhelp ==1.0.5 ; extra == 'docs'
Requires-Dist: sphinxcontrib-htmlhelp ==2.0.4 ; extra == 'docs'
Requires-Dist: sphinxcontrib-jsmath ==1.0.1 ; extra == 'docs'
Requires-Dist: sphinxcontrib-qthelp ==1.0.6 ; extra == 'docs'
Requires-Dist: sphinxcontrib-serializinghtml ==1.1.9 ; extra == 'docs'
Requires-Dist: urllib3 ==2.0.6 ; extra == 'docs'
Provides-Extra: tests
Requires-Dist: iniconfig ==2.0.0 ; extra == 'tests'
Requires-Dist: packaging ==23.2 ; extra == 'tests'
Requires-Dist: pluggy ==1.3.0 ; extra == 'tests'
Requires-Dist: pytest ==7.4.2 ; extra == 'tests'
Requires-Dist: pytest-randomly ==3.15.0 ; extra == 'tests'
